{
  "segments": [
    {
      "start": 10.831,
      "end": 29.447,
      "text": "從那遙遠海邊 慢慢消失的你本來模糊的臉 竟然漸漸清晰想要說些什麼 又不知從何說起只有把它放在心底",
      "words": [
        {
          "word": "從",
          "start": 10.831,
          "end": 10.931,
          "score": 0.8
        },
        {
          "word": "那",
          "start": 10.931,
          "end": 10.951,
          "score": 0.996
        },
        {
          "word": "遙",
          "start": 10.951,
          "end": 11.312,
          "score": 0.977
        },
        {
          "word": "遠",
          "start": 11.312,
          "end": 12.574,
          "score": 0.936
        },
        {
          "word": "海",
          "start": 12.574,
          "end": 12.594,
          "score": 0.773
        },
        {
          "word": "邊",
          "start": 12.594,
          "end": 13.456,
          "score": 0.999
        },
        {
          "word": "慢",
          "start": 13.757,
          "end": 14.017,
          "score": 0.923
        },
        {
          "word": "慢",
          "start": 14.017,
          "end": 14.037,
          "score": 0.872
        },
        {
          "word": "消",
          "start": 14.037,
          "end": 14.378,
          "score": 0.96
        },
        {
          "word": "失",
          "start": 14.378,
          "end": 14.739,
          "score": 0.941
        },
        {
          "word": "的",
          "start": 14.739,
          "end": 14.999,
          "score": 0.923
        },
        {
          "word": "你",
          "start": 14.999,
          "end": 16.001,
          "score": 0.999
        },
        {
          "word": "本",
          "start": 16.001,
          "end": 16.282,
          "score": 0.999
        },
        {
          "word": "來",
          "start": 16.282,
          "end": 16.562,
          "score": 0.958
        },
        {
          "word": "模",
          "start": 16.562,
          "end": 16.903,
          "score": 0.998
        },
        {
          "word": "糊",
          "start": 16.903,
          "end": 17.223,
          "score": 0.999
        },
        {
          "word": "的",
          "start": 17.223,
          "end": 17.524,
          "score": 0.985
        },
        {
          "word": "臉",
          "start": 17.524,
          "end": 18.125,
          "score": 0.982
        },
        {
          "word": "竟",
          "start": 18.706,
          "end": 18.726,
          "score": 0.0
        },
        {
          "word": "然",
          "start": 18.726,
          "end": 18.746,
          "score": 0.714
        },
        {
          "word": "漸",
          "start": 18.746,
          "end": 19.047,
          "score": 0.997
        },
        {
          "word": "漸",
          "start": 19.047,
          "end": 20.81,
          "score": 0.966
        },
        {
          "word": "清",
          "start": 20.81,
          "end": 20.83,
          "score": 0.0
        },
        {
          "word": "晰",
          "start": 20.83,
          "end": 20.85,
          "score": 0.884
        },
        {
          "word": "想",
          "start": 20.85,
          "end": 21.231,
          "score": 0.989
        },
        {
          "word": "要",
          "start": 21.231,
          "end": 21.492,
          "score": 1.0
        },
        {
          "word": "說",
          "start": 21.492,
          "end": 21.832,
          "score": 0.995
        },
        {
          "word": "些",
          "start": 21.832,
          "end": 22.113,
          "score": 0.929
        },
        {
          "word": "什",
          "start": 22.113,
          "end": 22.453,
          "score": 0.998
        },
        {
          "word": "麼",
          "start": 22.453,
          "end": 23.095,
          "score": 0.978
        },
        {
          "word": "又",
          "start": 23.375,
          "end": 23.395,
          "score": 0.765
        },
        {
          "word": "不",
          "start": 23.395,
          "end": 23.696,
          "score": 0.936
        },
        {
          "word": "知",
          "start": 23.696,
          "end": 23.996,
          "score": 0.981
        },
        {
          "word": "從",
          "start": 23.996,
          "end": 24.578,
          "score": 0.931
        },
        {
          "word": "何",
          "start": 24.578,
          "end": 24.598,
          "score": 0.989
        },
        {
          "word": "說",
          "start": 24.598,
          "end": 25.539,
          "score": 0.959
        },
        {
          "word": "起",
          "start": 25.539,
          "end": 25.56,
          "score": 0.44
        },
        {
          "word": "只",
          "start": 25.56,
          "end": 25.86,
          "score": 0.934
        },
        {
          "word": "有",
          "start": 25.86,
          "end": 26.181,
          "score": 0.965
        },
        {
          "word": "把",
          "start": 26.181,
          "end": 27.123,
          "score": 0.958
        },
        {
          "word": "它",
          "start": 27.123,
          "end": 27.143,
          "score": 0.626
        },
        {
          "word": "放",
          "start": 27.143,
          "end": 27.423,
          "score": 0.998
        },
        {
          "word": "在",
          "start": 27.423,
          "end": 28.024,
          "score": 0.952
        },
        {
          "word": "心",
          "start": 28.024,
          "end": 28.686,
          "score": 0.968
        },
        {
          "word": "底",
          "start": 28.686,
          "end": 29.447,
          "score": 0.946
        }
      ]
    },
    {
      "start": 31.587,
      "end": 58.81,
      "text": "茫然走在海边干那潮来潮去徒劳无功想把没多浪黄花几情想要说声爱你却被吹散在风里梦然回头你在哪里如果的还能够过会曾经的爱",
      "words": [
        {
          "word": "茫",
          "start": 31.587,
          "end": 32.308,
          "score": 0.889
        },
        {
          "word": "然",
          "start": 32.308,
          "end": 32.328,
          "score": 0.419
        },
        {
          "word": "走",
          "start": 32.328,
          "end": 32.629,
          "score": 0.961
        },
        {
          "word": "在",
          "start": 32.629,
          "end": 33.27,
          "score": 0.933
        },
        {
          "word": "海",
          "start": 33.27,
          "end": 33.29,
          "score": 0.701
        },
        {
          "word": "边",
          "start": 33.29,
          "end": 33.57,
          "score": 0.979
        },
        {
          "word": "干",
          "start": 33.57,
          "end": 33.851,
          "score": 0.933
        },
        {
          "word": "那",
          "start": 33.851,
          "end": 34.171,
          "score": 0.938
        },
        {
          "word": "潮",
          "start": 34.171,
          "end": 34.532,
          "score": 0.944
        },
        {
          "word": "来",
          "start": 34.532,
          "end": 34.812,
          "score": 0.928
        },
        {
          "word": "潮",
          "start": 34.812,
          "end": 35.413,
          "score": 0.966
        },
        {
          "word": "去",
          "start": 35.413,
          "end": 36.695,
          "score": 0.985
        },
        {
          "word": "徒",
          "start": 36.695,
          "end": 36.996,
          "score": 0.939
        },
        {
          "word": "劳",
          "start": 36.996,
          "end": 37.336,
          "score": 0.959
        },
        {
          "word": "无",
          "start": 37.336,
          "end": 37.617,
          "score": 0.929
        },
        {
          "word": "功",
          "start": 37.617,
          "end": 37.897,
          "score": 0.929
        },
        {
          "word": "想",
          "start": 37.897,
          "end": 38.498,
          "score": 0.898
        },
        {
          "word": "把",
          "start": 38.498,
          "end": 38.518,
          "score": 0.275
        },
        {
          "word": "没",
          "start": 38.518,
          "end": 39.159,
          "score": 0.998
        },
        {
          "word": "多",
          "start": 39.159,
          "end": 39.479,
          "score": 0.948
        },
        {
          "word": "浪",
          "start": 39.479,
          "end": 40.661,
          "score": 0.95
        },
        {
          "word": "黄",
          "start": 40.661,
          "end": 40.681,
          "score": 0.0
        },
        {
          "word": "花",
          "start": 40.681,
          "end": 40.701,
          "score": 0.005
        },
        {
          "word": "几",
          "start": 40.701,
          "end": 41.603,
          "score": 0.952
        },
        {
          "word": "情",
          "start": 41.603,
          "end": 41.623,
          "score": 0.053
        },
        {
          "word": "想",
          "start": 41.623,
          "end": 41.963,
          "score": 0.995
        },
        {
          "word": "要",
          "start": 41.963,
          "end": 42.244,
          "score": 0.998
        },
        {
          "word": "说",
          "start": 42.244,
          "end": 43.185,
          "score": 0.957
        },
        {
          "word": "声",
          "start": 43.185,
          "end": 43.205,
          "score": 0.029
        },
        {
          "word": "爱",
          "start": 43.205,
          "end": 43.526,
          "score": 0.942
        },
        {
          "word": "你",
          "start": 43.526,
          "end": 44.087,
          "score": 0.968
        },
        {
          "word": "却",
          "start": 44.087,
          "end": 44.467,
          "score": 0.996
        },
        {
          "word": "被",
          "start": 44.467,
          "end": 44.708,
          "score": 0.927
        },
        {
          "word": "吹",
          "start": 44.708,
          "end": 45.028,
          "score": 0.951
        },
        {
          "word": "散",
          "start": 45.028,
          "end": 45.349,
          "score": 0.995
        },
        {
          "word": "在",
          "start": 45.349,
          "end": 45.689,
          "score": 0.985
        },
        {
          "word": "风",
          "start": 45.689,
          "end": 46.05,
          "score": 0.945
        },
        {
          "word": "里",
          "start": 46.05,
          "end": 46.591,
          "score": 0.965
        },
        {
          "word": "梦",
          "start": 46.591,
          "end": 46.891,
          "score": 0.97
        },
        {
          "word": "然",
          "start": 46.891,
          "end": 47.252,
          "score": 0.937
        },
        {
          "word": "回",
          "start": 47.252,
          "end": 48.454,
          "score": 0.971
        },
        {
          "word": "头",
          "start": 48.454,
          "end": 48.474,
          "score": 0.036
        },
        {
          "word": "你",
          "start": 48.474,
          "end": 48.754,
          "score": 0.929
        },
        {
          "word": "在",
          "start": 48.754,
          "end": 51.218,
          "score": 0.979
        },
        {
          "word": "哪",
          "start": 51.218,
          "end": 51.238,
          "score": 0.0
        },
        {
          "word": "里",
          "start": 51.238,
          "end": 51.258,
          "score": 0.979
        },
        {
          "word": "如",
          "start": 51.258,
          "end": 51.839,
          "score": 0.967
        },
        {
          "word": "果",
          "start": 51.839,
          "end": 52.2,
          "score": 0.953
        },
        {
          "word": "的",
          "start": 52.2,
          "end": 53.361,
          "score": 0.976
        },
        {
          "word": "还",
          "start": 53.361,
          "end": 53.381,
          "score": 0.451
        },
        {
          "word": "能",
          "start": 53.381,
          "end": 54.563,
          "score": 0.95
        },
        {
          "word": "够",
          "start": 54.563,
          "end": 54.583,
          "score": 0.0
        },
        {
          "word": "过",
          "start": 54.583,
          "end": 54.603,
          "score": 0.441
        },
        {
          "word": "会",
          "start": 54.603,
          "end": 55.525,
          "score": 0.986
        },
        {
          "word": "曾",
          "start": 55.525,
          "end": 55.885,
          "score": 0.966
        },
        {
          "word": "经",
          "start": 55.885,
          "end": 56.506,
          "score": 0.937
        },
        {
          "word": "的",
          "start": 56.506,
          "end": 58.79,
          "score": 0.986
        },
        {
          "word": "爱",
          "start": 58.79,
          "end": 58.81,
          "score": 0.0
        }
      ]
    },
    {
      "start": 59.431,
      "end": 84.004,
      "text": "就讓我一生等的我 就如我一生等待說我的愛 我的愛 我的愛請全部帶走",
      "words": [
        {
          "word": "就",
          "start": 59.431,
          "end": 60.192,
          "score": 0.908
        },
        {
          "word": "讓",
          "start": 60.192,
          "end": 60.212,
          "score": 0.16
        },
        {
          "word": "我",
          "start": 60.212,
          "end": 63.777,
          "score": 0.968
        },
        {
          "word": "一",
          "start": 63.777,
          "end": 63.797,
          "score": 0.0
        },
        {
          "word": "生",
          "start": 63.797,
          "end": 63.817,
          "score": 0.0
        },
        {
          "word": "等",
          "start": 63.817,
          "end": 63.837,
          "score": 0.0
        },
        {
          "word": "的",
          "start": 63.837,
          "end": 63.857,
          "score": 0.0
        },
        {
          "word": "我",
          "start": 63.857,
          "end": 63.877,
          "score": 0.251
        },
        {
          "word": "就",
          "start": 64.237,
          "end": 64.257,
          "score": 0.254
        },
        {
          "word": "如",
          "start": 64.257,
          "end": 65.98,
          "score": 0.957
        },
        {
          "word": "我",
          "start": 65.98,
          "end": 66.0,
          "score": 0.0
        },
        {
          "word": "一",
          "start": 66.0,
          "end": 66.02,
          "score": 0.051
        },
        {
          "word": "生",
          "start": 66.02,
          "end": 67.001,
          "score": 0.992
        },
        {
          "word": "等",
          "start": 67.001,
          "end": 70.967,
          "score": 0.989
        },
        {
          "word": "待",
          "start": 70.967,
          "end": 70.987,
          "score": 0.376
        },
        {
          "word": "說",
          "start": 70.987,
          "end": 71.607,
          "score": 0.935
        },
        {
          "word": "我",
          "start": 71.607,
          "end": 71.627,
          "score": 0.95
        },
        {
          "word": "的",
          "start": 71.627,
          "end": 76.214,
          "score": 0.991
        },
        {
          "word": "愛",
          "start": 76.214,
          "end": 76.594,
          "score": 0.97
        },
        {
          "word": "我",
          "start": 78.757,
          "end": 79.097,
          "score": 0.992
        },
        {
          "word": "的",
          "start": 79.097,
          "end": 81.02,
          "score": 0.982
        },
        {
          "word": "愛",
          "start": 81.02,
          "end": 81.04,
          "score": 0.003
        },
        {
          "word": "我",
          "start": 81.06,
          "end": 81.08,
          "score": 0.0
        },
        {
          "word": "的",
          "start": 81.08,
          "end": 81.1,
          "score": 0.361
        },
        {
          "word": "愛",
          "start": 81.1,
          "end": 81.36,
          "score": 0.966
        },
        {
          "word": "請",
          "start": 81.36,
          "end": 81.741,
          "score": 0.945
        },
        {
          "word": "全",
          "start": 81.741,
          "end": 81.761,
          "score": 0.202
        },
        {
          "word": "部",
          "start": 81.761,
          "end": 82.482,
          "score": 0.992
        },
        {
          "word": "帶",
          "start": 82.482,
          "end": 83.984,
          "score": 0.973
        },
        {
          "word": "走",
          "start": 83.984,
          "end": 84.004,
          "score": 0.0
        }
      ]
    },
    {
      "start": 101.281,
      "end": 122.074,
      "text": "浪然坐在海边看那潮来潮去头脑无功想把没多冷化记忆倾向要说声爱你却被吹散在风里梦然回头你在哪里",
      "words": [
        {
          "word": "浪",
          "start": 101.281,
          "end": 102.202,
          "score": 0.935
        },
        {
          "word": "然",
          "start": 102.202,
          "end": 102.222,
          "score": 0.01
        },
        {
          "word": "坐",
          "start": 102.222,
          "end": 102.523,
          "score": 0.937
        },
        {
          "word": "在",
          "start": 102.523,
          "end": 103.464,
          "score": 0.958
        },
        {
          "word": "海",
          "start": 103.464,
          "end": 103.485,
          "score": 0.008
        },
        {
          "word": "边",
          "start": 103.485,
          "end": 103.785,
          "score": 0.944
        },
        {
          "word": "看",
          "start": 103.785,
          "end": 104.085,
          "score": 0.935
        },
        {
          "word": "那",
          "start": 104.085,
          "end": 104.366,
          "score": 0.928
        },
        {
          "word": "潮",
          "start": 104.366,
          "end": 104.726,
          "score": 0.987
        },
        {
          "word": "来",
          "start": 104.726,
          "end": 104.967,
          "score": 0.916
        },
        {
          "word": "潮",
          "start": 104.967,
          "end": 105.347,
          "score": 0.975
        },
        {
          "word": "去",
          "start": 105.347,
          "end": 106.549,
          "score": 0.981
        },
        {
          "word": "头",
          "start": 106.549,
          "end": 108.012,
          "score": 0.948
        },
        {
          "word": "脑",
          "start": 108.012,
          "end": 108.032,
          "score": 0.0
        },
        {
          "word": "无",
          "start": 108.032,
          "end": 108.052,
          "score": 0.0
        },
        {
          "word": "功",
          "start": 108.052,
          "end": 108.072,
          "score": 0.0
        },
        {
          "word": "想",
          "start": 108.072,
          "end": 108.432,
          "score": 0.945
        },
        {
          "word": "把",
          "start": 108.432,
          "end": 108.693,
          "score": 0.935
        },
        {
          "word": "没",
          "start": 108.693,
          "end": 109.033,
          "score": 0.992
        },
        {
          "word": "多",
          "start": 109.033,
          "end": 109.354,
          "score": 0.943
        },
        {
          "word": "冷",
          "start": 109.354,
          "end": 109.774,
          "score": 0.953
        },
        {
          "word": "化",
          "start": 109.774,
          "end": 110.816,
          "score": 0.959
        },
        {
          "word": "记",
          "start": 110.816,
          "end": 110.836,
          "score": 0.0
        },
        {
          "word": "忆",
          "start": 110.836,
          "end": 110.856,
          "score": 0.027
        },
        {
          "word": "倾",
          "start": 110.856,
          "end": 111.157,
          "score": 0.934
        },
        {
          "word": "向",
          "start": 111.157,
          "end": 111.477,
          "score": 0.987
        },
        {
          "word": "要",
          "start": 111.477,
          "end": 111.778,
          "score": 0.998
        },
        {
          "word": "说",
          "start": 111.778,
          "end": 112.098,
          "score": 0.94
        },
        {
          "word": "声",
          "start": 112.098,
          "end": 112.459,
          "score": 0.935
        },
        {
          "word": "爱",
          "start": 112.459,
          "end": 113.36,
          "score": 0.955
        },
        {
          "word": "你",
          "start": 113.36,
          "end": 113.38,
          "score": 0.579
        },
        {
          "word": "却",
          "start": 113.38,
          "end": 113.701,
          "score": 0.96
        },
        {
          "word": "被",
          "start": 113.701,
          "end": 113.961,
          "score": 0.931
        },
        {
          "word": "吹",
          "start": 113.961,
          "end": 114.602,
          "score": 0.938
        },
        {
          "word": "散",
          "start": 114.602,
          "end": 114.622,
          "score": 0.846
        },
        {
          "word": "在",
          "start": 114.622,
          "end": 114.963,
          "score": 0.988
        },
        {
          "word": "风",
          "start": 114.963,
          "end": 116.425,
          "score": 0.972
        },
        {
          "word": "里",
          "start": 116.425,
          "end": 116.445,
          "score": 0.008
        },
        {
          "word": "梦",
          "start": 116.445,
          "end": 116.766,
          "score": 0.938
        },
        {
          "word": "然",
          "start": 116.766,
          "end": 117.126,
          "score": 0.945
        },
        {
          "word": "回",
          "start": 117.126,
          "end": 117.407,
          "score": 0.941
        },
        {
          "word": "头",
          "start": 117.407,
          "end": 117.767,
          "score": 0.944
        },
        {
          "word": "你",
          "start": 117.767,
          "end": 118.328,
          "score": 0.994
        },
        {
          "word": "在",
          "start": 118.328,
          "end": 122.034,
          "score": 0.991
        },
        {
          "word": "哪",
          "start": 122.034,
          "end": 122.054,
          "score": 0.0
        },
        {
          "word": "里",
          "start": 122.054,
          "end": 122.074,
          "score": 0.0
        }
      ]
    },
    {
      "start": 122.83,
      "end": 149.243,
      "text": "如果大海能光回曾曾经的爱你真等待如果生起往事往事你不再流泪不再泪不再泪都让它随风飘走",
      "words": [
        {
          "word": "如",
          "start": 122.83,
          "end": 123.871,
          "score": 0.942
        },
        {
          "word": "果",
          "start": 123.871,
          "end": 123.891,
          "score": 0.061
        },
        {
          "word": "大",
          "start": 123.891,
          "end": 125.714,
          "score": 0.966
        },
        {
          "word": "海",
          "start": 125.714,
          "end": 125.734,
          "score": 0.0
        },
        {
          "word": "能",
          "start": 125.734,
          "end": 125.754,
          "score": 0.491
        },
        {
          "word": "光",
          "start": 125.754,
          "end": 126.374,
          "score": 0.998
        },
        {
          "word": "回",
          "start": 126.374,
          "end": 126.975,
          "score": 0.998
        },
        {
          "word": "曾",
          "start": 126.975,
          "end": 127.556,
          "score": 0.932
        },
        {
          "word": "曾",
          "start": 127.556,
          "end": 127.576,
          "score": 0.102
        },
        {
          "word": "经",
          "start": 127.576,
          "end": 128.217,
          "score": 0.988
        },
        {
          "word": "的",
          "start": 128.217,
          "end": 130.64,
          "score": 0.978
        },
        {
          "word": "爱",
          "start": 130.64,
          "end": 130.66,
          "score": 0.0
        },
        {
          "word": "你",
          "start": 130.66,
          "end": 130.68,
          "score": 0.435
        },
        {
          "word": "真",
          "start": 130.68,
          "end": 131.02,
          "score": 0.953
        },
        {
          "word": "等",
          "start": 131.02,
          "end": 133.163,
          "score": 0.981
        },
        {
          "word": "待",
          "start": 133.163,
          "end": 133.183,
          "score": 0.029
        },
        {
          "word": "如",
          "start": 133.183,
          "end": 133.483,
          "score": 0.939
        },
        {
          "word": "果",
          "start": 133.483,
          "end": 133.784,
          "score": 0.995
        },
        {
          "word": "生",
          "start": 133.784,
          "end": 138.309,
          "score": 0.96
        },
        {
          "word": "起",
          "start": 138.309,
          "end": 138.329,
          "score": 0.0
        },
        {
          "word": "往",
          "start": 138.329,
          "end": 138.349,
          "score": 0.0
        },
        {
          "word": "事",
          "start": 138.349,
          "end": 138.369,
          "score": 0.0
        },
        {
          "word": "往",
          "start": 138.369,
          "end": 138.389,
          "score": 0.0
        },
        {
          "word": "事",
          "start": 138.389,
          "end": 138.409,
          "score": 0.0
        },
        {
          "word": "你",
          "start": 138.409,
          "end": 138.43,
          "score": 0.0
        },
        {
          "word": "不",
          "start": 138.43,
          "end": 138.45,
          "score": 0.0
        },
        {
          "word": "再",
          "start": 138.45,
          "end": 138.47,
          "score": 0.03
        },
        {
          "word": "流",
          "start": 138.47,
          "end": 142.755,
          "score": 0.982
        },
        {
          "word": "泪",
          "start": 142.755,
          "end": 142.775,
          "score": 0.003
        },
        {
          "word": "不",
          "start": 142.775,
          "end": 145.739,
          "score": 0.975
        },
        {
          "word": "再",
          "start": 145.739,
          "end": 145.759,
          "score": 0.0
        },
        {
          "word": "泪",
          "start": 145.759,
          "end": 145.779,
          "score": 0.0
        },
        {
          "word": "不",
          "start": 145.779,
          "end": 145.799,
          "score": 0.0
        },
        {
          "word": "再",
          "start": 145.799,
          "end": 145.819,
          "score": 0.0
        },
        {
          "word": "泪",
          "start": 145.819,
          "end": 145.839,
          "score": 0.0
        },
        {
          "word": "都",
          "start": 145.839,
          "end": 145.859,
          "score": 0.898
        },
        {
          "word": "让",
          "start": 145.859,
          "end": 146.179,
          "score": 0.938
        },
        {
          "word": "它",
          "start": 146.179,
          "end": 146.5,
          "score": 0.998
        },
        {
          "word": "随",
          "start": 146.5,
          "end": 147.1,
          "score": 0.967
        },
        {
          "word": "风",
          "start": 147.1,
          "end": 147.441,
          "score": 0.941
        },
        {
          "word": "飘",
          "start": 147.441,
          "end": 148.642,
          "score": 0.984
        },
        {
          "word": "走",
          "start": 148.642,
          "end": 149.243,
          "score": 0.932
        }
      ]
    },
    {
      "start": 152.53,
      "end": 182.2,
      "text": "如果她還能夠帶帶走我的哀愁就像帶走每條河流所有的傷 所有有不顧的愛我的愛 進取不得",
      "words": [
        {
          "word": "如",
          "start": 152.53,
          "end": 153.231,
          "score": 0.943
        },
        {
          "word": "果",
          "start": 153.231,
          "end": 153.251,
          "score": 0.0
        },
        {
          "word": "她",
          "start": 153.251,
          "end": 153.271,
          "score": 0.406
        },
        {
          "word": "還",
          "start": 153.271,
          "end": 154.812,
          "score": 0.942
        },
        {
          "word": "能",
          "start": 154.812,
          "end": 154.832,
          "score": 0.188
        },
        {
          "word": "夠",
          "start": 154.832,
          "end": 155.473,
          "score": 0.975
        },
        {
          "word": "帶",
          "start": 155.473,
          "end": 156.054,
          "score": 0.972
        },
        {
          "word": "帶",
          "start": 156.054,
          "end": 157.275,
          "score": 0.976
        },
        {
          "word": "走",
          "start": 157.275,
          "end": 158.236,
          "score": 0.957
        },
        {
          "word": "我",
          "start": 158.236,
          "end": 158.256,
          "score": 0.931
        },
        {
          "word": "的",
          "start": 158.256,
          "end": 163.081,
          "score": 0.98
        },
        {
          "word": "哀",
          "start": 163.081,
          "end": 163.101,
          "score": 0.0
        },
        {
          "word": "愁",
          "start": 163.101,
          "end": 163.121,
          "score": 0.0
        },
        {
          "word": "就",
          "start": 163.121,
          "end": 163.141,
          "score": 0.114
        },
        {
          "word": "像",
          "start": 163.141,
          "end": 163.521,
          "score": 0.988
        },
        {
          "word": "帶",
          "start": 163.521,
          "end": 164.382,
          "score": 0.953
        },
        {
          "word": "走",
          "start": 164.382,
          "end": 164.402,
          "score": 0.017
        },
        {
          "word": "每",
          "start": 164.402,
          "end": 164.722,
          "score": 0.966
        },
        {
          "word": "條",
          "start": 164.722,
          "end": 165.643,
          "score": 0.988
        },
        {
          "word": "河",
          "start": 165.643,
          "end": 166.044,
          "score": 0.983
        },
        {
          "word": "流",
          "start": 166.044,
          "end": 167.465,
          "score": 1.0
        },
        {
          "word": "所",
          "start": 167.465,
          "end": 167.866,
          "score": 0.964
        },
        {
          "word": "有",
          "start": 167.866,
          "end": 168.146,
          "score": 0.999
        },
        {
          "word": "的",
          "start": 168.146,
          "end": 168.426,
          "score": 0.956
        },
        {
          "word": "傷",
          "start": 168.426,
          "end": 171.529,
          "score": 0.992
        },
        {
          "word": "所",
          "start": 175.133,
          "end": 175.153,
          "score": 0.0
        },
        {
          "word": "有",
          "start": 175.153,
          "end": 175.173,
          "score": 0.0
        },
        {
          "word": "有",
          "start": 175.173,
          "end": 175.193,
          "score": 0.0
        },
        {
          "word": "不",
          "start": 175.193,
          "end": 175.213,
          "score": 0.0
        },
        {
          "word": "顧",
          "start": 175.213,
          "end": 175.233,
          "score": 0.0
        },
        {
          "word": "的",
          "start": 175.233,
          "end": 175.253,
          "score": 0.127
        },
        {
          "word": "愛",
          "start": 175.253,
          "end": 175.553,
          "score": 0.932
        },
        {
          "word": "我",
          "start": 175.553,
          "end": 175.573,
          "score": 0.988
        },
        {
          "word": "的",
          "start": 175.573,
          "end": 177.395,
          "score": 0.983
        },
        {
          "word": "愛",
          "start": 177.395,
          "end": 177.756,
          "score": 0.965
        },
        {
          "word": "進",
          "start": 178.036,
          "end": 182.14,
          "score": 0.995
        },
        {
          "word": "取",
          "start": 182.14,
          "end": 182.16,
          "score": 0.0
        },
        {
          "word": "不",
          "start": 182.16,
          "end": 182.18,
          "score": 0.0
        },
        {
          "word": "得",
          "start": 182.18,
          "end": 182.2,
          "score": 0.0
        }
      ]
    },
    {
      "start": 182.956,
      "end": 199.48,
      "text": "我大概能够带走我的哀愁就像带带走没走没跳河流所有受过了伤所有流",
      "words": [
        {
          "word": "我",
          "start": 182.956,
          "end": 183.858,
          "score": 0.92
        },
        {
          "word": "大",
          "start": 183.858,
          "end": 183.878,
          "score": 0.0
        },
        {
          "word": "概",
          "start": 183.878,
          "end": 183.899,
          "score": 0.699
        },
        {
          "word": "能",
          "start": 183.899,
          "end": 184.219,
          "score": 0.953
        },
        {
          "word": "够",
          "start": 184.219,
          "end": 184.5,
          "score": 0.962
        },
        {
          "word": "带",
          "start": 184.5,
          "end": 185.403,
          "score": 0.938
        },
        {
          "word": "走",
          "start": 185.403,
          "end": 185.423,
          "score": 0.0
        },
        {
          "word": "我",
          "start": 185.423,
          "end": 185.443,
          "score": 0.998
        },
        {
          "word": "的",
          "start": 185.443,
          "end": 186.044,
          "score": 0.933
        },
        {
          "word": "哀",
          "start": 186.044,
          "end": 186.064,
          "score": 0.001
        },
        {
          "word": "愁",
          "start": 186.064,
          "end": 187.267,
          "score": 0.996
        },
        {
          "word": "就",
          "start": 187.267,
          "end": 187.568,
          "score": 0.961
        },
        {
          "word": "像",
          "start": 187.568,
          "end": 187.929,
          "score": 0.948
        },
        {
          "word": "带",
          "start": 187.929,
          "end": 188.25,
          "score": 0.95
        },
        {
          "word": "带",
          "start": 188.25,
          "end": 189.132,
          "score": 0.934
        },
        {
          "word": "走",
          "start": 189.132,
          "end": 189.153,
          "score": 0.102
        },
        {
          "word": "没",
          "start": 189.153,
          "end": 189.714,
          "score": 0.93
        },
        {
          "word": "走",
          "start": 189.714,
          "end": 189.734,
          "score": 0.088
        },
        {
          "word": "没",
          "start": 189.734,
          "end": 190.075,
          "score": 0.94
        },
        {
          "word": "跳",
          "start": 190.075,
          "end": 190.376,
          "score": 0.988
        },
        {
          "word": "河",
          "start": 190.376,
          "end": 190.797,
          "score": 0.981
        },
        {
          "word": "流",
          "start": 190.797,
          "end": 192.862,
          "score": 0.99
        },
        {
          "word": "所",
          "start": 192.862,
          "end": 193.945,
          "score": 0.948
        },
        {
          "word": "有",
          "start": 193.945,
          "end": 193.965,
          "score": 0.0
        },
        {
          "word": "受",
          "start": 193.965,
          "end": 193.985,
          "score": 0.079
        },
        {
          "word": "过",
          "start": 193.985,
          "end": 194.467,
          "score": 0.966
        },
        {
          "word": "了",
          "start": 194.467,
          "end": 197.194,
          "score": 0.983
        },
        {
          "word": "伤",
          "start": 197.194,
          "end": 197.214,
          "score": 0.449
        },
        {
          "word": "所",
          "start": 197.214,
          "end": 197.856,
          "score": 0.968
        },
        {
          "word": "有",
          "start": 197.856,
          "end": 198.157,
          "score": 0.937
        },
        {
          "word": "流",
          "start": 198.157,
          "end": 199.48,
          "score": 0.952
        }
      ]
    },
    {
      "start": 201.147,
      "end": 221.94,
      "text": "就像帶走完就像帶走完就像帶走沒走過不流流所有流磨磨磨的戀愛情緒不得力活該",
      "words": [
        {
          "word": "就",
          "start": 201.147,
          "end": 201.187,
          "score": 0.5
        },
        {
          "word": "像",
          "start": 201.187,
          "end": 201.207,
          "score": 0.985
        },
        {
          "word": "帶",
          "start": 201.207,
          "end": 202.99,
          "score": 0.955
        },
        {
          "word": "走",
          "start": 202.99,
          "end": 203.01,
          "score": 0.0
        },
        {
          "word": "完",
          "start": 203.01,
          "end": 203.03,
          "score": 0.0
        },
        {
          "word": "就",
          "start": 203.03,
          "end": 203.05,
          "score": 0.0
        },
        {
          "word": "像",
          "start": 203.05,
          "end": 203.07,
          "score": 0.532
        },
        {
          "word": "帶",
          "start": 203.07,
          "end": 204.853,
          "score": 0.963
        },
        {
          "word": "走",
          "start": 204.853,
          "end": 204.873,
          "score": 0.0
        },
        {
          "word": "完",
          "start": 204.873,
          "end": 204.893,
          "score": 0.833
        },
        {
          "word": "就",
          "start": 204.893,
          "end": 205.534,
          "score": 0.941
        },
        {
          "word": "像",
          "start": 205.534,
          "end": 205.554,
          "score": 0.702
        },
        {
          "word": "帶",
          "start": 205.554,
          "end": 207.377,
          "score": 0.937
        },
        {
          "word": "走",
          "start": 207.377,
          "end": 207.397,
          "score": 0.0
        },
        {
          "word": "沒",
          "start": 207.397,
          "end": 207.417,
          "score": 0.0
        },
        {
          "word": "走",
          "start": 207.417,
          "end": 207.437,
          "score": 0.17
        },
        {
          "word": "過",
          "start": 207.437,
          "end": 209.741,
          "score": 0.958
        },
        {
          "word": "不",
          "start": 209.741,
          "end": 209.761,
          "score": 0.0
        },
        {
          "word": "流",
          "start": 209.761,
          "end": 209.781,
          "score": 0.0
        },
        {
          "word": "流",
          "start": 209.781,
          "end": 209.801,
          "score": 0.717
        },
        {
          "word": "所",
          "start": 209.801,
          "end": 211.984,
          "score": 0.947
        },
        {
          "word": "有",
          "start": 211.984,
          "end": 212.004,
          "score": 0.0
        },
        {
          "word": "流",
          "start": 212.004,
          "end": 212.024,
          "score": 0.0
        },
        {
          "word": "磨",
          "start": 212.024,
          "end": 212.044,
          "score": 0.0
        },
        {
          "word": "磨",
          "start": 212.044,
          "end": 212.064,
          "score": 0.0
        },
        {
          "word": "磨",
          "start": 212.064,
          "end": 212.084,
          "score": 0.314
        },
        {
          "word": "的",
          "start": 212.084,
          "end": 215.43,
          "score": 0.982
        },
        {
          "word": "戀",
          "start": 215.43,
          "end": 215.67,
          "score": 0.917
        },
        {
          "word": "愛",
          "start": 215.67,
          "end": 215.69,
          "score": 0.0
        },
        {
          "word": "情",
          "start": 215.69,
          "end": 215.71,
          "score": 0.795
        },
        {
          "word": "緒",
          "start": 215.71,
          "end": 216.251,
          "score": 0.963
        },
        {
          "word": "不",
          "start": 216.251,
          "end": 217.613,
          "score": 0.971
        },
        {
          "word": "得",
          "start": 217.613,
          "end": 217.633,
          "score": 0.103
        },
        {
          "word": "力",
          "start": 217.633,
          "end": 221.9,
          "score": 0.988
        },
        {
          "word": "活",
          "start": 221.9,
          "end": 221.92,
          "score": 0.001
        },
        {
          "word": "該",
          "start": 221.92,
          "end": 221.94,
          "score": 0.012
        }
      ]
    }
  ],
  "word_segments": [
    {
      "word": "從",
      "start": 10.831,
      "end": 10.931,
      "score": 0.8
    },
    {
      "word": "那",
      "start": 10.931,
      "end": 10.951,
      "score": 0.996
    },
    {
      "word": "遙",
      "start": 10.951,
      "end": 11.312,
      "score": 0.977
    },
    {
      "word": "遠",
      "start": 11.312,
      "end": 12.574,
      "score": 0.936
    },
    {
      "word": "海",
      "start": 12.574,
      "end": 12.594,
      "score": 0.773
    },
    {
      "word": "邊",
      "start": 12.594,
      "end": 13.456,
      "score": 0.999
    },
    {
      "word": "慢",
      "start": 13.757,
      "end": 14.017,
      "score": 0.923
    },
    {
      "word": "慢",
      "start": 14.017,
      "end": 14.037,
      "score": 0.872
    },
    {
      "word": "消",
      "start": 14.037,
      "end": 14.378,
      "score": 0.96
    },
    {
      "word": "失",
      "start": 14.378,
      "end": 14.739,
      "score": 0.941
    },
    {
      "word": "的",
      "start": 14.739,
      "end": 14.999,
      "score": 0.923
    },
    {
      "word": "你",
      "start": 14.999,
      "end": 16.001,
      "score": 0.999
    },
    {
      "word": "本",
      "start": 16.001,
      "end": 16.282,
      "score": 0.999
    },
    {
      "word": "來",
      "start": 16.282,
      "end": 16.562,
      "score": 0.958
    },
    {
      "word": "模",
      "start": 16.562,
      "end": 16.903,
      "score": 0.998
    },
    {
      "word": "糊",
      "start": 16.903,
      "end": 17.223,
      "score": 0.999
    },
    {
      "word": "的",
      "start": 17.223,
      "end": 17.524,
      "score": 0.985
    },
    {
      "word": "臉",
      "start": 17.524,
      "end": 18.125,
      "score": 0.982
    },
    {
      "word": "竟",
      "start": 18.706,
      "end": 18.726,
      "score": 0.0
    },
    {
      "word": "然",
      "start": 18.726,
      "end": 18.746,
      "score": 0.714
    },
    {
      "word": "漸",
      "start": 18.746,
      "end": 19.047,
      "score": 0.997
    },
    {
      "word": "漸",
      "start": 19.047,
      "end": 20.81,
      "score": 0.966
    },
    {
      "word": "清",
      "start": 20.81,
      "end": 20.83,
      "score": 0.0
    },
    {
      "word": "晰",
      "start": 20.83,
      "end": 20.85,
      "score": 0.884
    },
    {
      "word": "想",
      "start": 20.85,
      "end": 21.231,
      "score": 0.989
    },
    {
      "word": "要",
      "start": 21.231,
      "end": 21.492,
      "score": 1.0
    },
    {
      "word": "說",
      "start": 21.492,
      "end": 21.832,
      "score": 0.995
    },
    {
      "word": "些",
      "start": 21.832,
      "end": 22.113,
      "score": 0.929
    },
    {
      "word": "什",
      "start": 22.113,
      "end": 22.453,
      "score": 0.998
    },
    {
      "word": "麼",
      "start": 22.453,
      "end": 23.095,
      "score": 0.978
    },
    {
      "word": "又",
      "start": 23.375,
      "end": 23.395,
      "score": 0.765
    },
    {
      "word": "不",
      "start": 23.395,
      "end": 23.696,
      "score": 0.936
    },
    {
      "word": "知",
      "start": 23.696,
      "end": 23.996,
      "score": 0.981
    },
    {
      "word": "從",
      "start": 23.996,
      "end": 24.578,
      "score": 0.931
    },
    {
      "word": "何",
      "start": 24.578,
      "end": 24.598,
      "score": 0.989
    },
    {
      "word": "說",
      "start": 24.598,
      "end": 25.539,
      "score": 0.959
    },
    {
      "word": "起",
      "start": 25.539,
      "end": 25.56,
      "score": 0.44
    },
    {
      "word": "只",
      "start": 25.56,
      "end": 25.86,
      "score": 0.934
    },
    {
      "word": "有",
      "start": 25.86,
      "end": 26.181,
      "score": 0.965
    },
    {
      "word": "把",
      "start": 26.181,
      "end": 27.123,
      "score": 0.958
    },
    {
      "word": "它",
      "start": 27.123,
      "end": 27.143,
      "score": 0.626
    },
    {
      "word": "放",
      "start": 27.143,
      "end": 27.423,
      "score": 0.998
    },
    {
      "word": "在",
      "start": 27.423,
      "end": 28.024,
      "score": 0.952
    },
    {
      "word": "心",
      "start": 28.024,
      "end": 28.686,
      "score": 0.968
    },
    {
      "word": "底",
      "start": 28.686,
      "end": 29.447,
      "score": 0.946
    },
    {
      "word": "茫",
      "start": 31.587,
      "end": 32.308,
      "score": 0.889
    },
    {
      "word": "然",
      "start": 32.308,
      "end": 32.328,
      "score": 0.419
    },
    {
      "word": "走",
      "start": 32.328,
      "end": 32.629,
      "score": 0.961
    },
    {
      "word": "在",
      "start": 32.629,
      "end": 33.27,
      "score": 0.933
    },
    {
      "word": "海",
      "start": 33.27,
      "end": 33.29,
      "score": 0.701
    },
    {
      "word": "边",
      "start": 33.29,
      "end": 33.57,
      "score": 0.979
    },
    {
      "word": "干",
      "start": 33.57,
      "end": 33.851,
      "score": 0.933
    },
    {
      "word": "那",
      "start": 33.851,
      "end": 34.171,
      "score": 0.938
    },
    {
      "word": "潮",
      "start": 34.171,
      "end": 34.532,
      "score": 0.944
    },
    {
      "word": "来",
      "start": 34.532,
      "end": 34.812,
      "score": 0.928
    },
    {
      "word": "潮",
      "start": 34.812,
      "end": 35.413,
      "score": 0.966
    },
    {
      "word": "去",
      "start": 35.413,
      "end": 36.695,
      "score": 0.985
    },
    {
      "word": "徒",
      "start": 36.695,
      "end": 36.996,
      "score": 0.939
    },
    {
      "word": "劳",
      "start": 36.996,
      "end": 37.336,
      "score": 0.959
    },
    {
      "word": "无",
      "start": 37.336,
      "end": 37.617,
      "score": 0.929
    },
    {
      "word": "功",
      "start": 37.617,
      "end": 37.897,
      "score": 0.929
    },
    {
      "word": "想",
      "start": 37.897,
      "end": 38.498,
      "score": 0.898
    },
    {
      "word": "把",
      "start": 38.498,
      "end": 38.518,
      "score": 0.275
    },
    {
      "word": "没",
      "start": 38.518,
      "end": 39.159,
      "score": 0.998
    },
    {
      "word": "多",
      "start": 39.159,
      "end": 39.479,
      "score": 0.948
    },
    {
      "word": "浪",
      "start": 39.479,
      "end": 40.661,
      "score": 0.95
    },
    {
      "word": "黄",
      "start": 40.661,
      "end": 40.681,
      "score": 0.0
    },
    {
      "word": "花",
      "start": 40.681,
      "end": 40.701,
      "score": 0.005
    },
    {
      "word": "几",
      "start": 40.701,
      "end": 41.603,
      "score": 0.952
    },
    {
      "word": "情",
      "start": 41.603,
      "end": 41.623,
      "score": 0.053
    },
    {
      "word": "想",
      "start": 41.623,
      "end": 41.963,
      "score": 0.995
    },
    {
      "word": "要",
      "start": 41.963,
      "end": 42.244,
      "score": 0.998
    },
    {
      "word": "说",
      "start": 42.244,
      "end": 43.185,
      "score": 0.957
    },
    {
      "word": "声",
      "start": 43.185,
      "end": 43.205,
      "score": 0.029
    },
    {
      "word": "爱",
      "start": 43.205,
      "end": 43.526,
      "score": 0.942
    },
    {
      "word": "你",
      "start": 43.526,
      "end": 44.087,
      "score": 0.968
    },
    {
      "word": "却",
      "start": 44.087,
      "end": 44.467,
      "score": 0.996
    },
    {
      "word": "被",
      "start": 44.467,
      "end": 44.708,
      "score": 0.927
    },
    {
      "word": "吹",
      "start": 44.708,
      "end": 45.028,
      "score": 0.951
    },
    {
      "word": "散",
      "start": 45.028,
      "end": 45.349,
      "score": 0.995
    },
    {
      "word": "在",
      "start": 45.349,
      "end": 45.689,
      "score": 0.985
    },
    {
      "word": "风",
      "start": 45.689,
      "end": 46.05,
      "score": 0.945
    },
    {
      "word": "里",
      "start": 46.05,
      "end": 46.591,
      "score": 0.965
    },
    {
      "word": "梦",
      "start": 46.591,
      "end": 46.891,
      "score": 0.97
    },
    {
      "word": "然",
      "start": 46.891,
      "end": 47.252,
      "score": 0.937
    },
    {
      "word": "回",
      "start": 47.252,
      "end": 48.454,
      "score": 0.971
    },
    {
      "word": "头",
      "start": 48.454,
      "end": 48.474,
      "score": 0.036
    },
    {
      "word": "你",
      "start": 48.474,
      "end": 48.754,
      "score": 0.929
    },
    {
      "word": "在",
      "start": 48.754,
      "end": 51.218,
      "score": 0.979
    },
    {
      "word": "哪",
      "start": 51.218,
      "end": 51.238,
      "score": 0.0
    },
    {
      "word": "里",
      "start": 51.238,
      "end": 51.258,
      "score": 0.979
    },
    {
      "word": "如",
      "start": 51.258,
      "end": 51.839,
      "score": 0.967
    },
    {
      "word": "果",
      "start": 51.839,
      "end": 52.2,
      "score": 0.953
    },
    {
      "word": "的",
      "start": 52.2,
      "end": 53.361,
      "score": 0.976
    },
    {
      "word": "还",
      "start": 53.361,
      "end": 53.381,
      "score": 0.451
    },
    {
      "word": "能",
      "start": 53.381,
      "end": 54.563,
      "score": 0.95
    },
    {
      "word": "够",
      "start": 54.563,
      "end": 54.583,
      "score": 0.0
    },
    {
      "word": "过",
      "start": 54.583,
      "end": 54.603,
      "score": 0.441
    },
    {
      "word": "会",
      "start": 54.603,
      "end": 55.525,
      "score": 0.986
    },
    {
      "word": "曾",
      "start": 55.525,
      "end": 55.885,
      "score": 0.966
    },
    {
      "word": "经",
      "start": 55.885,
      "end": 56.506,
      "score": 0.937
    },
    {
      "word": "的",
      "start": 56.506,
      "end": 58.79,
      "score": 0.986
    },
    {
      "word": "爱",
      "start": 58.79,
      "end": 58.81,
      "score": 0.0
    },
    {
      "word": "就",
      "start": 59.431,
      "end": 60.192,
      "score": 0.908
    },
    {
      "word": "讓",
      "start": 60.192,
      "end": 60.212,
      "score": 0.16
    },
    {
      "word": "我",
      "start": 60.212,
      "end": 63.777,
      "score": 0.968
    },
    {
      "word": "一",
      "start": 63.777,
      "end": 63.797,
      "score": 0.0
    },
    {
      "word": "生",
      "start": 63.797,
      "end": 63.817,
      "score": 0.0
    },
    {
      "word": "等",
      "start": 63.817,
      "end": 63.837,
      "score": 0.0
    },
    {
      "word": "的",
      "start": 63.837,
      "end": 63.857,
      "score": 0.0
    },
    {
      "word": "我",
      "start": 63.857,
      "end": 63.877,
      "score": 0.251
    },
    {
      "word": "就",
      "start": 64.237,
      "end": 64.257,
      "score": 0.254
    },
    {
      "word": "如",
      "start": 64.257,
      "end": 65.98,
      "score": 0.957
    },
    {
      "word": "我",
      "start": 65.98,
      "end": 66.0,
      "score": 0.0
    },
    {
      "word": "一",
      "start": 66.0,
      "end": 66.02,
      "score": 0.051
    },
    {
      "word": "生",
      "start": 66.02,
      "end": 67.001,
      "score": 0.992
    },
    {
      "word": "等",
      "start": 67.001,
      "end": 70.967,
      "score": 0.989
    },
    {
      "word": "待",
      "start": 70.967,
      "end": 70.987,
      "score": 0.376
    },
    {
      "word": "說",
      "start": 70.987,
      "end": 71.607,
      "score": 0.935
    },
    {
      "word": "我",
      "start": 71.607,
      "end": 71.627,
      "score": 0.95
    },
    {
      "word": "的",
      "start": 71.627,
      "end": 76.214,
      "score": 0.991
    },
    {
      "word": "愛",
      "start": 76.214,
      "end": 76.594,
      "score": 0.97
    },
    {
      "word": "我",
      "start": 78.757,
      "end": 79.097,
      "score": 0.992
    },
    {
      "word": "的",
      "start": 79.097,
      "end": 81.02,
      "score": 0.982
    },
    {
      "word": "愛",
      "start": 81.02,
      "end": 81.04,
      "score": 0.003
    },
    {
      "word": "我",
      "start": 81.06,
      "end": 81.08,
      "score": 0.0
    },
    {
      "word": "的",
      "start": 81.08,
      "end": 81.1,
      "score": 0.361
    },
    {
      "word": "愛",
      "start": 81.1,
      "end": 81.36,
      "score": 0.966
    },
    {
      "word": "請",
      "start": 81.36,
      "end": 81.741,
      "score": 0.945
    },
    {
      "word": "全",
      "start": 81.741,
      "end": 81.761,
      "score": 0.202
    },
    {
      "word": "部",
      "start": 81.761,
      "end": 82.482,
      "score": 0.992
    },
    {
      "word": "帶",
      "start": 82.482,
      "end": 83.984,
      "score": 0.973
    },
    {
      "word": "走",
      "start": 83.984,
      "end": 84.004,
      "score": 0.0
    },
    {
      "word": "浪",
      "start": 101.281,
      "end": 102.202,
      "score": 0.935
    },
    {
      "word": "然",
      "start": 102.202,
      "end": 102.222,
      "score": 0.01
    },
    {
      "word": "坐",
      "start": 102.222,
      "end": 102.523,
      "score": 0.937
    },
    {
      "word": "在",
      "start": 102.523,
      "end": 103.464,
      "score": 0.958
    },
    {
      "word": "海",
      "start": 103.464,
      "end": 103.485,
      "score": 0.008
    },
    {
      "word": "边",
      "start": 103.485,
      "end": 103.785,
      "score": 0.944
    },
    {
      "word": "看",
      "start": 103.785,
      "end": 104.085,
      "score": 0.935
    },
    {
      "word": "那",
      "start": 104.085,
      "end": 104.366,
      "score": 0.928
    },
    {
      "word": "潮",
      "start": 104.366,
      "end": 104.726,
      "score": 0.987
    },
    {
      "word": "来",
      "start": 104.726,
      "end": 104.967,
      "score": 0.916
    },
    {
      "word": "潮",
      "start": 104.967,
      "end": 105.347,
      "score": 0.975
    },
    {
      "word": "去",
      "start": 105.347,
      "end": 106.549,
      "score": 0.981
    },
    {
      "word": "头",
      "start": 106.549,
      "end": 108.012,
      "score": 0.948
    },
    {
      "word": "脑",
      "start": 108.012,
      "end": 108.032,
      "score": 0.0
    },
    {
      "word": "无",
      "start": 108.032,
      "end": 108.052,
      "score": 0.0
    },
    {
      "word": "功",
      "start": 108.052,
      "end": 108.072,
      "score": 0.0
    },
    {
      "word": "想",
      "start": 108.072,
      "end": 108.432,
      "score": 0.945
    },
    {
      "word": "把",
      "start": 108.432,
      "end": 108.693,
      "score": 0.935
    },
    {
      "word": "没",
      "start": 108.693,
      "end": 109.033,
      "score": 0.992
    },
    {
      "word": "多",
      "start": 109.033,
      "end": 109.354,
      "score": 0.943
    },
    {
      "word": "冷",
      "start": 109.354,
      "end": 109.774,
      "score": 0.953
    },
    {
      "word": "化",
      "start": 109.774,
      "end": 110.816,
      "score": 0.959
    },
    {
      "word": "记",
      "start": 110.816,
      "end": 110.836,
      "score": 0.0
    },
    {
      "word": "忆",
      "start": 110.836,
      "end": 110.856,
      "score": 0.027
    },
    {
      "word": "倾",
      "start": 110.856,
      "end": 111.157,
      "score": 0.934
    },
    {
      "word": "向",
      "start": 111.157,
      "end": 111.477,
      "score": 0.987
    },
    {
      "word": "要",
      "start": 111.477,
      "end": 111.778,
      "score": 0.998
    },
    {
      "word": "说",
      "start": 111.778,
      "end": 112.098,
      "score": 0.94
    },
    {
      "word": "声",
      "start": 112.098,
      "end": 112.459,
      "score": 0.935
    },
    {
      "word": "爱",
      "start": 112.459,
      "end": 113.36,
      "score": 0.955
    },
    {
      "word": "你",
      "start": 113.36,
      "end": 113.38,
      "score": 0.579
    },
    {
      "word": "却",
      "start": 113.38,
      "end": 113.701,
      "score": 0.96
    },
    {
      "word": "被",
      "start": 113.701,
      "end": 113.961,
      "score": 0.931
    },
    {
      "word": "吹",
      "start": 113.961,
      "end": 114.602,
      "score": 0.938
    },
    {
      "word": "散",
      "start": 114.602,
      "end": 114.622,
      "score": 0.846
    },
    {
      "word": "在",
      "start": 114.622,
      "end": 114.963,
      "score": 0.988
    },
    {
      "word": "风",
      "start": 114.963,
      "end": 116.425,
      "score": 0.972
    },
    {
      "word": "里",
      "start": 116.425,
      "end": 116.445,
      "score": 0.008
    },
    {
      "word": "梦",
      "start": 116.445,
      "end": 116.766,
      "score": 0.938
    },
    {
      "word": "然",
      "start": 116.766,
      "end": 117.126,
      "score": 0.945
    },
    {
      "word": "回",
      "start": 117.126,
      "end": 117.407,
      "score": 0.941
    },
    {
      "word": "头",
      "start": 117.407,
      "end": 117.767,
      "score": 0.944
    },
    {
      "word": "你",
      "start": 117.767,
      "end": 118.328,
      "score": 0.994
    },
    {
      "word": "在",
      "start": 118.328,
      "end": 122.034,
      "score": 0.991
    },
    {
      "word": "哪",
      "start": 122.034,
      "end": 122.054,
      "score": 0.0
    },
    {
      "word": "里",
      "start": 122.054,
      "end": 122.074,
      "score": 0.0
    },
    {
      "word": "如",
      "start": 122.83,
      "end": 123.871,
      "score": 0.942
    },
    {
      "word": "果",
      "start": 123.871,
      "end": 123.891,
      "score": 0.061
    },
    {
      "word": "大",
      "start": 123.891,
      "end": 125.714,
      "score": 0.966
    },
    {
      "word": "海",
      "start": 125.714,
      "end": 125.734,
      "score": 0.0
    },
    {
      "word": "能",
      "start": 125.734,
      "end": 125.754,
      "score": 0.491
    },
    {
      "word": "光",
      "start": 125.754,
      "end": 126.374,
      "score": 0.998
    },
    {
      "word": "回",
      "start": 126.374,
      "end": 126.975,
      "score": 0.998
    },
    {
      "word": "曾",
      "start": 126.975,
      "end": 127.556,
      "score": 0.932
    },
    {
      "word": "曾",
      "start": 127.556,
      "end": 127.576,
      "score": 0.102
    },
    {
      "word": "经",
      "start": 127.576,
      "end": 128.217,
      "score": 0.988
    },
    {
      "word": "的",
      "start": 128.217,
      "end": 130.64,
      "score": 0.978
    },
    {
      "word": "爱",
      "start": 130.64,
      "end": 130.66,
      "score": 0.0
    },
    {
      "word": "你",
      "start": 130.66,
      "end": 130.68,
      "score": 0.435
    },
    {
      "word": "真",
      "start": 130.68,
      "end": 131.02,
      "score": 0.953
    },
    {
      "word": "等",
      "start": 131.02,
      "end": 133.163,
      "score": 0.981
    },
    {
      "word": "待",
      "start": 133.163,
      "end": 133.183,
      "score": 0.029
    },
    {
      "word": "如",
      "start": 133.183,
      "end": 133.483,
      "score": 0.939
    },
    {
      "word": "果",
      "start": 133.483,
      "end": 133.784,
      "score": 0.995
    },
    {
      "word": "生",
      "start": 133.784,
      "end": 138.309,
      "score": 0.96
    },
    {
      "word": "起",
      "start": 138.309,
      "end": 138.329,
      "score": 0.0
    },
    {
      "word": "往",
      "start": 138.329,
      "end": 138.349,
      "score": 0.0
    },
    {
      "word": "事",
      "start": 138.349,
      "end": 138.369,
      "score": 0.0
    },
    {
      "word": "往",
      "start": 138.369,
      "end": 138.389,
      "score": 0.0
    },
    {
      "word": "事",
      "start": 138.389,
      "end": 138.409,
      "score": 0.0
    },
    {
      "word": "你",
      "start": 138.409,
      "end": 138.43,
      "score": 0.0
    },
    {
      "word": "不",
      "start": 138.43,
      "end": 138.45,
      "score": 0.0
    },
    {
      "word": "再",
      "start": 138.45,
      "end": 138.47,
      "score": 0.03
    },
    {
      "word": "流",
      "start": 138.47,
      "end": 142.755,
      "score": 0.982
    },
    {
      "word": "泪",
      "start": 142.755,
      "end": 142.775,
      "score": 0.003
    },
    {
      "word": "不",
      "start": 142.775,
      "end": 145.739,
      "score": 0.975
    },
    {
      "word": "再",
      "start": 145.739,
      "end": 145.759,
      "score": 0.0
    },
    {
      "word": "泪",
      "start": 145.759,
      "end": 145.779,
      "score": 0.0
    },
    {
      "word": "不",
      "start": 145.779,
      "end": 145.799,
      "score": 0.0
    },
    {
      "word": "再",
      "start": 145.799,
      "end": 145.819,
      "score": 0.0
    },
    {
      "word": "泪",
      "start": 145.819,
      "end": 145.839,
      "score": 0.0
    },
    {
      "word": "都",
      "start": 145.839,
      "end": 145.859,
      "score": 0.898
    },
    {
      "word": "让",
      "start": 145.859,
      "end": 146.179,
      "score": 0.938
    },
    {
      "word": "它",
      "start": 146.179,
      "end": 146.5,
      "score": 0.998
    },
    {
      "word": "随",
      "start": 146.5,
      "end": 147.1,
      "score": 0.967
    },
    {
      "word": "风",
      "start": 147.1,
      "end": 147.441,
      "score": 0.941
    },
    {
      "word": "飘",
      "start": 147.441,
      "end": 148.642,
      "score": 0.984
    },
    {
      "word": "走",
      "start": 148.642,
      "end": 149.243,
      "score": 0.932
    },
    {
      "word": "如",
      "start": 152.53,
      "end": 153.231,
      "score": 0.943
    },
    {
      "word": "果",
      "start": 153.231,
      "end": 153.251,
      "score": 0.0
    },
    {
      "word": "她",
      "start": 153.251,
      "end": 153.271,
      "score": 0.406
    },
    {
      "word": "還",
      "start": 153.271,
      "end": 154.812,
      "score": 0.942
    },
    {
      "word": "能",
      "start": 154.812,
      "end": 154.832,
      "score": 0.188
    },
    {
      "word": "夠",
      "start": 154.832,
      "end": 155.473,
      "score": 0.975
    },
    {
      "word": "帶",
      "start": 155.473,
      "end": 156.054,
      "score": 0.972
    },
    {
      "word": "帶",
      "start": 156.054,
      "end": 157.275,
      "score": 0.976
    },
    {
      "word": "走",
      "start": 157.275,
      "end": 158.236,
      "score": 0.957
    },
    {
      "word": "我",
      "start": 158.236,
      "end": 158.256,
      "score": 0.931
    },
    {
      "word": "的",
      "start": 158.256,
      "end": 163.081,
      "score": 0.98
    },
    {
      "word": "哀",
      "start": 163.081,
      "end": 163.101,
      "score": 0.0
    },
    {
      "word": "愁",
      "start": 163.101,
      "end": 163.121,
      "score": 0.0
    },
    {
      "word": "就",
      "start": 163.121,
      "end": 163.141,
      "score": 0.114
    },
    {
      "word": "像",
      "start": 163.141,
      "end": 163.521,
      "score": 0.988
    },
    {
      "word": "帶",
      "start": 163.521,
      "end": 164.382,
      "score": 0.953
    },
    {
      "word": "走",
      "start": 164.382,
      "end": 164.402,
      "score": 0.017
    },
    {
      "word": "每",
      "start": 164.402,
      "end": 164.722,
      "score": 0.966
    },
    {
      "word": "條",
      "start": 164.722,
      "end": 165.643,
      "score": 0.988
    },
    {
      "word": "河",
      "start": 165.643,
      "end": 166.044,
      "score": 0.983
    },
    {
      "word": "流",
      "start": 166.044,
      "end": 167.465,
      "score": 1.0
    },
    {
      "word": "所",
      "start": 167.465,
      "end": 167.866,
      "score": 0.964
    },
    {
      "word": "有",
      "start": 167.866,
      "end": 168.146,
      "score": 0.999
    },
    {
      "word": "的",
      "start": 168.146,
      "end": 168.426,
      "score": 0.956
    },
    {
      "word": "傷",
      "start": 168.426,
      "end": 171.529,
      "score": 0.992
    },
    {
      "word": "所",
      "start": 175.133,
      "end": 175.153,
      "score": 0.0
    },
    {
      "word": "有",
      "start": 175.153,
      "end": 175.173,
      "score": 0.0
    },
    {
      "word": "有",
      "start": 175.173,
      "end": 175.193,
      "score": 0.0
    },
    {
      "word": "不",
      "start": 175.193,
      "end": 175.213,
      "score": 0.0
    },
    {
      "word": "顧",
      "start": 175.213,
      "end": 175.233,
      "score": 0.0
    },
    {
      "word": "的",
      "start": 175.233,
      "end": 175.253,
      "score": 0.127
    },
    {
      "word": "愛",
      "start": 175.253,
      "end": 175.553,
      "score": 0.932
    },
    {
      "word": "我",
      "start": 175.553,
      "end": 175.573,
      "score": 0.988
    },
    {
      "word": "的",
      "start": 175.573,
      "end": 177.395,
      "score": 0.983
    },
    {
      "word": "愛",
      "start": 177.395,
      "end": 177.756,
      "score": 0.965
    },
    {
      "word": "進",
      "start": 178.036,
      "end": 182.14,
      "score": 0.995
    },
    {
      "word": "取",
      "start": 182.14,
      "end": 182.16,
      "score": 0.0
    },
    {
      "word": "不",
      "start": 182.16,
      "end": 182.18,
      "score": 0.0
    },
    {
      "word": "得",
      "start": 182.18,
      "end": 182.2,
      "score": 0.0
    },
    {
      "word": "我",
      "start": 182.956,
      "end": 183.858,
      "score": 0.92
    },
    {
      "word": "大",
      "start": 183.858,
      "end": 183.878,
      "score": 0.0
    },
    {
      "word": "概",
      "start": 183.878,
      "end": 183.899,
      "score": 0.699
    },
    {
      "word": "能",
      "start": 183.899,
      "end": 184.219,
      "score": 0.953
    },
    {
      "word": "够",
      "start": 184.219,
      "end": 184.5,
      "score": 0.962
    },
    {
      "word": "带",
      "start": 184.5,
      "end": 185.403,
      "score": 0.938
    },
    {
      "word": "走",
      "start": 185.403,
      "end": 185.423,
      "score": 0.0
    },
    {
      "word": "我",
      "start": 185.423,
      "end": 185.443,
      "score": 0.998
    },
    {
      "word": "的",
      "start": 185.443,
      "end": 186.044,
      "score": 0.933
    },
    {
      "word": "哀",
      "start": 186.044,
      "end": 186.064,
      "score": 0.001
    },
    {
      "word": "愁",
      "start": 186.064,
      "end": 187.267,
      "score": 0.996
    },
    {
      "word": "就",
      "start": 187.267,
      "end": 187.568,
      "score": 0.961
    },
    {
      "word": "像",
      "start": 187.568,
      "end": 187.929,
      "score": 0.948
    },
    {
      "word": "带",
      "start": 187.929,
      "end": 188.25,
      "score": 0.95
    },
    {
      "word": "带",
      "start": 188.25,
      "end": 189.132,
      "score": 0.934
    },
    {
      "word": "走",
      "start": 189.132,
      "end": 189.153,
      "score": 0.102
    },
    {
      "word": "没",
      "start": 189.153,
      "end": 189.714,
      "score": 0.93
    },
    {
      "word": "走",
      "start": 189.714,
      "end": 189.734,
      "score": 0.088
    },
    {
      "word": "没",
      "start": 189.734,
      "end": 190.075,
      "score": 0.94
    },
    {
      "word": "跳",
      "start": 190.075,
      "end": 190.376,
      "score": 0.988
    },
    {
      "word": "河",
      "start": 190.376,
      "end": 190.797,
      "score": 0.981
    },
    {
      "word": "流",
      "start": 190.797,
      "end": 192.862,
      "score": 0.99
    },
    {
      "word": "所",
      "start": 192.862,
      "end": 193.945,
      "score": 0.948
    },
    {
      "word": "有",
      "start": 193.945,
      "end": 193.965,
      "score": 0.0
    },
    {
      "word": "受",
      "start": 193.965,
      "end": 193.985,
      "score": 0.079
    },
    {
      "word": "过",
      "start": 193.985,
      "end": 194.467,
      "score": 0.966
    },
    {
      "word": "了",
      "start": 194.467,
      "end": 197.194,
      "score": 0.983
    },
    {
      "word": "伤",
      "start": 197.194,
      "end": 197.214,
      "score": 0.449
    },
    {
      "word": "所",
      "start": 197.214,
      "end": 197.856,
      "score": 0.968
    },
    {
      "word": "有",
      "start": 197.856,
      "end": 198.157,
      "score": 0.937
    },
    {
      "word": "流",
      "start": 198.157,
      "end": 199.48,
      "score": 0.952
    },
    {
      "word": "就",
      "start": 201.147,
      "end": 201.187,
      "score": 0.5
    },
    {
      "word": "像",
      "start": 201.187,
      "end": 201.207,
      "score": 0.985
    },
    {
      "word": "帶",
      "start": 201.207,
      "end": 202.99,
      "score": 0.955
    },
    {
      "word": "走",
      "start": 202.99,
      "end": 203.01,
      "score": 0.0
    },
    {
      "word": "完",
      "start": 203.01,
      "end": 203.03,
      "score": 0.0
    },
    {
      "word": "就",
      "start": 203.03,
      "end": 203.05,
      "score": 0.0
    },
    {
      "word": "像",
      "start": 203.05,
      "end": 203.07,
      "score": 0.532
    },
    {
      "word": "帶",
      "start": 203.07,
      "end": 204.853,
      "score": 0.963
    },
    {
      "word": "走",
      "start": 204.853,
      "end": 204.873,
      "score": 0.0
    },
    {
      "word": "完",
      "start": 204.873,
      "end": 204.893,
      "score": 0.833
    },
    {
      "word": "就",
      "start": 204.893,
      "end": 205.534,
      "score": 0.941
    },
    {
      "word": "像",
      "start": 205.534,
      "end": 205.554,
      "score": 0.702
    },
    {
      "word": "帶",
      "start": 205.554,
      "end": 207.377,
      "score": 0.937
    },
    {
      "word": "走",
      "start": 207.377,
      "end": 207.397,
      "score": 0.0
    },
    {
      "word": "沒",
      "start": 207.397,
      "end": 207.417,
      "score": 0.0
    },
    {
      "word": "走",
      "start": 207.417,
      "end": 207.437,
      "score": 0.17
    },
    {
      "word": "過",
      "start": 207.437,
      "end": 209.741,
      "score": 0.958
    },
    {
      "word": "不",
      "start": 209.741,
      "end": 209.761,
      "score": 0.0
    },
    {
      "word": "流",
      "start": 209.761,
      "end": 209.781,
      "score": 0.0
    },
    {
      "word": "流",
      "start": 209.781,
      "end": 209.801,
      "score": 0.717
    },
    {
      "word": "所",
      "start": 209.801,
      "end": 211.984,
      "score": 0.947
    },
    {
      "word": "有",
      "start": 211.984,
      "end": 212.004,
      "score": 0.0
    },
    {
      "word": "流",
      "start": 212.004,
      "end": 212.024,
      "score": 0.0
    },
    {
      "word": "磨",
      "start": 212.024,
      "end": 212.044,
      "score": 0.0
    },
    {
      "word": "磨",
      "start": 212.044,
      "end": 212.064,
      "score": 0.0
    },
    {
      "word": "磨",
      "start": 212.064,
      "end": 212.084,
      "score": 0.314
    },
    {
      "word": "的",
      "start": 212.084,
      "end": 215.43,
      "score": 0.982
    },
    {
      "word": "戀",
      "start": 215.43,
      "end": 215.67,
      "score": 0.917
    },
    {
      "word": "愛",
      "start": 215.67,
      "end": 215.69,
      "score": 0.0
    },
    {
      "word": "情",
      "start": 215.69,
      "end": 215.71,
      "score": 0.795
    },
    {
      "word": "緒",
      "start": 215.71,
      "end": 216.251,
      "score": 0.963
    },
    {
      "word": "不",
      "start": 216.251,
      "end": 217.613,
      "score": 0.971
    },
    {
      "word": "得",
      "start": 217.613,
      "end": 217.633,
      "score": 0.103
    },
    {
      "word": "力",
      "start": 217.633,
      "end": 221.9,
      "score": 0.988
    },
    {
      "word": "活",
      "start": 221.9,
      "end": 221.92,
      "score": 0.001
    },
    {
      "word": "該",
      "start": 221.92,
      "end": 221.94,
      "score": 0.012
    }
  ],
  "language": "zh"
}